odoo/addons/base_geoengine/README.rst
odoo/addons/base_geoengine/__init__.py
odoo/addons/base_geoengine/__manifest__.py
odoo/addons/base_geoengine/expressions.py
odoo/addons/base_geoengine/fields.py
odoo/addons/base_geoengine/geo_convertion_helper.py
odoo/addons/base_geoengine/geo_db.py
odoo/addons/base_geoengine/geo_operators.py
odoo/addons/base_geoengine/i18n/base_geoengine.pot
odoo/addons/base_geoengine/i18n/es.po
odoo/addons/base_geoengine/i18n/fr_BE.po
odoo/addons/base_geoengine/i18n/it.po
odoo/addons/base_geoengine/i18n/sv.po
odoo/addons/base_geoengine/i18n/zh_CN.po
odoo/addons/base_geoengine/images/map-hover.png
odoo/addons/base_geoengine/images/map.png
odoo/addons/base_geoengine/models/__init__.py
odoo/addons/base_geoengine/models/base.py
odoo/addons/base_geoengine/models/geo_raster_layer.py
odoo/addons/base_geoengine/models/geo_vector_layer.py
odoo/addons/base_geoengine/models/ir_model.py
odoo/addons/base_geoengine/models/ir_view.py
odoo/addons/base_geoengine/readme/CONTRIBUTORS.md
odoo/addons/base_geoengine/readme/DESCRIPTION.md
odoo/addons/base_geoengine/readme/HISTORY.md
odoo/addons/base_geoengine/readme/INSTALL.md
odoo/addons/base_geoengine/readme/ROADMAP.md
odoo/addons/base_geoengine/readme/USAGE.md
odoo/addons/base_geoengine/security/data.xml
odoo/addons/base_geoengine/security/ir.model.access.csv
odoo/addons/base_geoengine/static/description/icon.png
odoo/addons/base_geoengine/static/description/index.html
odoo/addons/base_geoengine/static/img/map-marker.png
odoo/addons/base_geoengine/static/lib/chromajs-3.1.2/LICENSE
odoo/addons/base_geoengine/static/lib/chromajs-3.1.2/chroma.js
odoo/addons/base_geoengine/static/lib/geostats-2.1.0/geostats.css
odoo/addons/base_geoengine/static/lib/geostats-2.1.0/geostats.js
odoo/addons/base_geoengine/static/lib/ol-10.5.0/ol.js
odoo/addons/base_geoengine/static/lib/ol-10.5.0/ol.js.map
odoo/addons/base_geoengine/static/src/css/style.css
odoo/addons/base_geoengine/static/src/images/editing_tool_bar.png
odoo_addon_base_geoengine-18.0.1.0.1.3.dist-info/METADATA
odoo_addon_base_geoengine-18.0.1.0.1.3.dist-info/WHEEL
odoo_addon_base_geoengine-18.0.1.0.1.3.dist-info/top_level.txt
odoo_addon_base_geoengine-18.0.1.0.1.3.dist-info/RECORD
