Metadata-Version: 2.1
Name: odoo-addon-base_geoengine
Version: 18.0.1.0.1.3
Requires-Python: >=3.10
Requires-Dist: geojson
Requires-Dist: odoo==18.0.*
Requires-Dist: shapely
Summary: Geospatial support for Odoo
Home-page: https://github.com/OCA/geospatial
License: AGPL-3
Author: Camptocamp,ACSONE SA/NV,Odoo Community Association (OCA)
Author-email: support@odoo-community.org
Classifier: Programming Language :: Python
Classifier: Framework :: Odoo
Classifier: Framework :: Odoo :: 18.0
Classifier: License :: OSI Approved :: GNU Affero General Public License v3
